google_music_scripts/__about__.py
google_music_scripts/__init__.py
google_music_scripts/__main__.py
google_music_scripts/cli.py
google_music_scripts/commands.py
google_music_scripts/config.py
google_music_scripts/constants.py
google_music_scripts/core.py
google_music_scripts/utils.py
google_music_scripts-4.5.0.dist-info/entry_points.txt
google_music_scripts-4.5.0.dist-info/LICENSE
google_music_scripts-4.5.0.dist-info/WHEEL
google_music_scripts-4.5.0.dist-info/METADATA
google_music_scripts-4.5.0.dist-info/RECORD
