Metadata-Version: 2.1
Name: google-music-scripts
Version: 4.5.0
Summary: A CLI utility for interacting with Google Music.
Home-page: https://github.com/thebigmunch/google-music-scripts
License: MIT
Author: thebigmunch
Author-email: mail@thebigmunch.me
Requires-Python: >=3.6,<4.0
Classifier: License :: OSI Approved :: MIT License
Classifier: Programming Language :: Python :: 3
Classifier: Programming Language :: Python :: 3.6
Classifier: Programming Language :: Python :: 3.7
Classifier: Programming Language :: Python :: 3.8
Provides-Extra: dev
Provides-Extra: doc
Provides-Extra: lint
Requires-Dist: appdirs (>=1.0,<2.0)
Requires-Dist: attrs (>=18.2,<19.4)
Requires-Dist: audio-metadata (>=0.10)
Requires-Dist: flake8 (>=3.5,<4.0); extra == "dev" or extra == "lint"
Requires-Dist: flake8-builtins (>=1.0,<2.0); extra == "dev" or extra == "lint"
Requires-Dist: flake8-comprehensions (>=2.0,<=4.0); extra == "dev" or extra == "lint"
Requires-Dist: flake8-import-order (>=0.18,<0.19); extra == "dev" or extra == "lint"
Requires-Dist: flake8-import-order-tbm (>=1.2,<2.0); extra == "dev" or extra == "lint"
Requires-Dist: google-music (>=3.4,<4.0)
Requires-Dist: google-music-proto (>=2.8,<3.0)
Requires-Dist: google-music-utils (>=2.1,<3.0)
Requires-Dist: loguru (>=0.4.0,<0.5.0)
Requires-Dist: natsort (>=5.0,<8.0)
Requires-Dist: nox (>=2019,<2020); extra == "dev"
Requires-Dist: pendulum (>=2.0,<=3.0,!=2.0.5,!=2.1.0)
Requires-Dist: pprintpp (<1.0.0)
Requires-Dist: sphinx (>=2.0,<3.0); extra == "dev" or extra == "doc"
Requires-Dist: sphinx-argparse (>=0.2,<0.3); extra == "dev" or extra == "doc"
Requires-Dist: sphinx-material (<1.0.0); extra == "dev" or extra == "doc"
Requires-Dist: tbm-utils (>=2.3,<3.0)
Requires-Dist: tomlkit (>=0.5,<0.6)
Project-URL: Repository, https://github.com/thebigmunch/google-music-scripts
